dcore/__init__.py
dcore/admin.py
dcore/api_functions.py
dcore/api_mixins.py
dcore/api_utils.py
dcore/apps.py
dcore/commands.py
dcore/contexts.py
dcore/date_utils.py
dcore/dependency_settings.py
dcore/enums.py
dcore/exceptions.py
dcore/form_fields.py
dcore/form_utils.py
dcore/managers.py
dcore/middleware.py
dcore/model_fields.py
dcore/models.py
dcore/serializers.py
dcore/service.py
dcore/test_utils.py
dcore/tests.py
dcore/utils.py
dcore/validation_utils.py
dcore/validators.py
dcore/views.py
dcore/locale/cs/LC_MESSAGES/django.po
dcore/migrations/__init__.py
dcore/static/.gitkeep
dcore/templates/.gitkeep
dcore/templatetags/__init__.py
dcore/templatetags/dcore_extras.py
django_dcore-0.34.dist-info/LICENSE
django_dcore-0.34.dist-info/METADATA
django_dcore-0.34.dist-info/WHEEL
django_dcore-0.34.dist-info/top_level.txt
django_dcore-0.34.dist-info/RECORD
